LICENSE
MANIFEST.in
README.md
setup.py
django_lineage.egg-info/PKG-INFO
django_lineage.egg-info/SOURCES.txt
django_lineage.egg-info/dependency_links.txt
django_lineage.egg-info/top_level.txt
lineage/__init__.py
lineage/models.py
lineage/settings.py
lineage/templatetags/__init__.py
lineage/templatetags/lineage.py