Metadata-Version: 1.0
Name: django-lineage
Version: 0.2.0
Summary: Lightweight template tags for neater hierarchical navigation
Home-page: https://github.com/marcuswhybrow/django-lineage
Author: Marcus Whybrow
Author-email: pypi@marcuswhybrow.net
License: BSD
Download-URL: https://github.com/marcuswhybrow/django-lineage/downloads
Platform: UNKNOWN
Classifier: Programming Language :: Python
Classifier: Development Status :: 3 - Alpha
Classifier: Framework :: Django
Classifier: Intended Audience :: Developers
Classifier: Operating System :: OS Independent
Classifier: License :: OSI Approved :: BSD License
Classifier: Topic :: Software Development :: Libraries :: Python Modules
Classifier: Topic :: System :: Distributed Computing
